bundle.py
bundle_cpp-0.1.8.dist-info/METADATA
bundle_cpp-0.1.8.dist-info/WHEEL
bundle_cpp-0.1.8.dist-info/entry_points.txt
bundle_cpp-0.1.8.dist-info/RECORD
