Metadata-Version: 2.3
Name: bundle-cpp
Version: 0.1.8
Summary: expand includes and create a single file
License: MIT
Author: kagemeka
Author-email: kagemeka1@gmail.com
Requires-Python: >=3.12,<4.0
Classifier: License :: OSI Approved :: MIT License
Classifier: Programming Language :: Python :: 3
Classifier: Programming Language :: Python :: 3.12
Classifier: Programming Language :: Python :: 3.13
